TCT/TCT.py
TCT/TCT_Visualization.py
TCT/__init__.py
TCT/name_resolver.py
TCT/node_normalizer.py
TCT/server.py
TCT/translator_kpinfo.py
TCT/translator_metakg.py
TCT/translator_node.py
TCT/translator_query.py
TCT/trapi.py
tct-0.1.6.dist-info/METADATA
tct-0.1.6.dist-info/WHEEL
tct-0.1.6.dist-info/entry_points.txt
tct-0.1.6.dist-info/RECORD
