Metadata-Version: 2.4
Name: TCT
Version: 0.1.6
Summary: Translator Component Toolkit
Project-URL: Homepage, https://github.com/NCATSTranslator/Translator_component_toolkit
Project-URL: Documentation, https://ncatstranslator.github.io/Translator_component_toolkit/
Project-URL: Repository, https://github.com/NCATSTranslator/Translator_component_toolkit
Author: Guangrong Qin, Yue Zhang, Sierra Moxon
License: MIT
Classifier: Development Status :: 4 - Beta
Classifier: Intended Audience :: Developers
Classifier: License :: OSI Approved :: MIT License
Classifier: Programming Language :: Python :: 3
Classifier: Programming Language :: Python :: 3.10
Classifier: Programming Language :: Python :: 3.11
Requires-Python: >=3.10
Requires-Dist: click>=8.2.1
Requires-Dist: fastmcp>=2.12.2
Requires-Dist: ipycytoscape
Requires-Dist: ipykernel
Requires-Dist: jsons
Requires-Dist: matplotlib
Requires-Dist: networkx
Requires-Dist: numpy
Requires-Dist: openai
Requires-Dist: pandas
Requires-Dist: pyvis
Requires-Dist: requests
Requires-Dist: seaborn
